fbratelegram/__init__.py
fbratelegram/client.py
fbratelegram/examples/__init__.py
fbratelegram/examples/asyncio_to_thread.py
fbratelegram/examples/quick_start.py
fbratelegram/extras/__init__.py
fbratelegram/extras/config_parser.py
fbratelegram/extras/crypto.py
fbratelegram/extras/stderr_logger.py
fbra_telegram-0.0.7.dist-info/LICENSE
fbra_telegram-0.0.7.dist-info/METADATA
fbra_telegram-0.0.7.dist-info/WHEEL
fbra_telegram-0.0.7.dist-info/top_level.txt
fbra_telegram-0.0.7.dist-info/RECORD
