Metadata-Version: 2.1
Name: fbra-telegram
Version: 0.0.7
Summary: Send Messages to Telegram
Author: Felix Brändli
Author-email: 
Keywords: python,python-telegram-bot,wrapper
Classifier: Programming Language :: Python :: 3
Classifier: License :: OSI Approved :: MIT License
Classifier: Operating System :: OS Independent
Requires-Python: >=3.10
License-File: LICENSE
Requires-Dist: python-telegram-bot[ext]
Requires-Dist: fbra-crypto
